docker_hostdns/__init__.py
docker_hostdns/__main__.py
docker_hostdns/console.py
docker_hostdns/exceptions.py
docker_hostdns/hostdns.py
docker_hostdns-2.4.0.dist-info/METADATA
docker_hostdns-2.4.0.dist-info/WHEEL
docker_hostdns-2.4.0.dist-info/entry_points.txt
docker_hostdns-2.4.0.dist-info/top_level.txt
docker_hostdns-2.4.0.dist-info/zip-safe
docker_hostdns-2.4.0.dist-info/RECORD
