Metadata-Version: 2.1
Name: docker-hostdns
Version: 2.4.0
Summary: Update BIND nameserver zone with Docker hosts via DNS Updates.
Home-page: https://github.com/glorpen/docker-hostdns
Author: Arkadiusz Dzięgiel
Author-email: arkadiusz.dziegiel@glorpen.pl
License: UNKNOWN
Keywords: docker dns bind named
Platform: UNKNOWN
Classifier: Programming Language :: Python
Classifier: Development Status :: 5 - Production/Stable
Classifier: Intended Audience :: Developers
Classifier: Intended Audience :: System Administrators
Classifier: License :: OSI Approved :: GNU General Public License v3 or later (GPLv3+)
Classifier: Programming Language :: Python :: 3 :: Only
Classifier: Topic :: Software Development
Classifier: Topic :: Utilities
Requires-Dist: docker (>=2.0.0)
Requires-Dist: dnspython (>=1.13.0)
Provides-Extra: development
Requires-Dist: unittest ; extra == 'development'
Requires-Dist: python-daemon ; extra == 'development'
Provides-Extra: suggested
Requires-Dist: python-daemon ; extra == 'suggested'
Provides-Extra: testing
Requires-Dist: unittest ; extra == 'testing'
Requires-Dist: python-daemon ; extra == 'testing'
